cipher_fl/AES.py
cipher_fl/DES.py
cipher_fl/RSA.py
cipher_fl/__init__.py
cipher_fl-2.0.0.dist-info/METADATA
cipher_fl-2.0.0.dist-info/WHEEL
cipher_fl-2.0.0.dist-info/top_level.txt
cipher_fl-2.0.0.dist-info/RECORD
