Metadata-Version: 2.1
Name: cipher_fl
Version: 2.0.0
Summary: 一个包含AES、DES、RSA加密模块的包
Author: FengLing
Author-email: damon__dong@163.com
License: MIT
Classifier: Programming Language :: Python :: 3
Classifier: License :: OSI Approved :: MIT License
Classifier: Operating System :: OS Independent
Requires-Python: >=3.8
